genderbyrusname/__init__.py
genderbyrusname/genderbyrusname.py
gender_by_rus_name-0.0.6.dist-info/LICENSE
gender_by_rus_name-0.0.6.dist-info/METADATA
gender_by_rus_name-0.0.6.dist-info/WHEEL
gender_by_rus_name-0.0.6.dist-info/top_level.txt
gender_by_rus_name-0.0.6.dist-info/RECORD
